slg_dev_ops/__init__.py
slg_dev_ops/digital_ocean_api.py
slg_dev_ops/install_nginx.py
slg_dev_ops-1.21.24.data/scripts/add-to-env
slg_dev_ops-1.21.24.data/scripts/slg-build-cron-jobs
slg_dev_ops-1.21.24.data/scripts/slg-create-bash-script
slg_dev_ops-1.21.24.data/scripts/slg-create-digital-ocean-droplet
slg_dev_ops-1.21.24.data/scripts/slg-create-python-script
slg_dev_ops-1.21.24.data/scripts/slg-digital-ocean-droplet-setup
slg_dev_ops-1.21.24.data/scripts/slg-git-clone-default-username
slg_dev_ops-1.21.24.data/scripts/slg-git-make-repo-subdir-into-submodule
slg_dev_ops-1.21.24.data/scripts/slg-git-release
slg_dev_ops-1.21.24.data/scripts/slg-git-remove-submodule
slg_dev_ops-1.21.24.data/scripts/slg-git-setup-gh
slg_dev_ops-1.21.24.data/scripts/slg-init-gunicorn-systemd-services
slg_dev_ops-1.21.24.data/scripts/slg-init-nginx-conf-gunicorn
slg_dev_ops-1.21.24.data/scripts/slg-init-remote-crontab
slg_dev_ops-1.21.24.data/scripts/slg-install-ansible
slg_dev_ops-1.21.24.data/scripts/slg-install-dotfiles
slg_dev_ops-1.21.24.data/scripts/slg-install-firewall
slg_dev_ops-1.21.24.data/scripts/slg-install-nginx
slg_dev_ops-1.21.24.data/scripts/slg-install-service-with-stopped-notification
slg_dev_ops-1.21.24.data/scripts/slg-nginx-reverse-proxy-to-multiple-https-sites
slg_dev_ops-1.21.24.data/scripts/slg-restart-docker-container
slg_dev_ops-1.21.24.data/scripts/slg-setup-ssl
slg_dev_ops-1.21.24.data/scripts/slg-setup-tls-for-domains
slg_dev_ops-1.21.24.data/scripts/slg-setup-tls-ssl-nginx
slg_dev_ops-1.21.24.data/scripts/slg-spin-up-entire-server-with-nginx-https-website
slg_dev_ops-1.21.24.data/scripts/slg-time-logger
slg_dev_ops-1.21.24.data/scripts/slg-time-logger-consolidate
slg_dev_ops-1.21.24.dist-info/METADATA
slg_dev_ops-1.21.24.dist-info/WHEEL
slg_dev_ops-1.21.24.dist-info/top_level.txt
slg_dev_ops-1.21.24.dist-info/RECORD
