Metadata-Version: 2.4
Name: slg-dev-ops
Version: 1.21.24
Summary: This is a description.
Requires-Python: >=3.6.3
Requires-Dist: logger-slg
Requires-Dist: slg-script-helpers>=0.1.5
Dynamic: description
Dynamic: description-content-type
Dynamic: requires-dist
Dynamic: requires-python
Dynamic: summary
